{
  "data": {
    "providers": [
      {
        "name": "Staked",
        "logoUrl": "https://storage.googleapis.com/stakingrewards-static/images/providers/production/eigenlayer/0x6573629204b65faac121c1b556b91a694d0e23c8.png",
        "country": "us",
        "rewardOptions": [
          {
            "id": "5d34930fe03dd8000780b7a3",
            "type": {
              "key": "pos",
              "label": "pos"
            },
            "metrics": [
              {
                "metricKey": "30d_apr",
                "defaultValue": 0.08998984800567686
              },
              {
                "metricKey": "activation_time",
                "defaultValue": 1532036007.0
              }
            ]
          },
          {
            "id": "5ef361ad97cfa00007ba4596",
            "type": {
              "key": "pos",
              "label": "pos"
            },
            "metrics": [
              {
                "metricKey": "assets_under_management",
                "defaultValue": 2250598.868104798
              },
              {
                "metricKey": "available_capacity",
                "defaultValue": 0
              }
            ]
          },
          {
            "id": "5ef6218d41746e0008003c0f",
            "type": {
              "key": "pos",
              "label": "pos"
            },
            "metrics": [
              {
                "metricKey": "lockup_time",
                "defaultValue": 1239035.0
              },
              {
                "metricKey": "minimum",
                "defaultValue": 0
              }
            ]
          },
          {
            "id": "5ef622268105cb0007142f17",
            "type": {
              "key": "pos",
              "label": "pos"
            },
            "metrics": [
              {
                "metricKey": "assets_under_management",
                "defaultValue": 311043299.044154
              },
              {
                "metricKey": "available_capacity",
                "defaultValue": 0
              }
            ]
          },
          {
            "id": "5ef62302b3a6250007455b00",
            "type": {
              "key": "pos",
              "label": "pos"
            },
            "metrics": [
              {
                "metricKey": "minimum",
                "defaultValue": 0
              },
              {
                "metricKey": "reward_frequency",
                "defaultValue": 604800
              }
            ]
          }
        ]
      },
      {
        "name": "Figment",
        "logoUrl": "https://storage.googleapis.com/stakingrewards-static/images/providers/production/figment_logo.png?random=0.725224064232785",
        "country": "CA",
        "rewardOptions": [
          {
            "id": "5f05c86c3ff67100084831e1",
            "type": {
              "key": "pos",
              "label": "pos"
            },
            "metrics": [
              {
                "metricKey": "assets_under_management",
                "defaultValue": 140523.69470203426
              },
              {
                "metricKey": "available_capacity",
                "defaultValue": 0
              }
            ]
          },
          {
            "id": "5f884f4b79d36100077ec8f7",
            "type": {
              "key": "pos",
              "label": "pos"
            },
            "metrics": [
              {
                "metricKey": "assets_under_management",
                "defaultValue": 62745767.59978991
              },
              {
                "metricKey": "available_capacity",
                "defaultValue": 0
              }
            ]
          },
          {
            "id": "5ff6d5221acf780007736bb8",
            "type": {
              "key": "pos",
              "label": "pos"
            },
            "metrics": [
              {
                "metricKey": "assets_under_management",
                "defaultValue": 2042889.9465273388
              },
              {
                "metricKey": "bounty_per_month",
                "defaultValue": 2481170.944958082
              }
            ]
          },
          {
            "id": "602cda8df12a3a0007b376ac",
            "type": {
              "key": "pos",
              "label": "pos"
            },
            "metrics": [
              {
                "metricKey": "assets_under_management",
                "defaultValue": 1661414531.2643225
              },
              {
                "metricKey": "available_capacity",
                "defaultValue": 0
              }
            ]
          },
          {
            "id": "623b6166216825000900ba0d",
            "type": {
              "key": "pos",
              "label": "pos"
            },
            "metrics": [
              {
                "metricKey": "assets_under_management",
                "defaultValue": 12349019.640845858
              },
              {
                "metricKey": "available_capacity",
                "defaultValue": 0
              }
            ]
          }
        ]
      },
      {
        "name": "Chorus One",
        "logoUrl": "https://storage.googleapis.com/stakingrewards-static/images/providers/production/eigenlayer/0xf80b7ba7e778abf08a63426886ca40189c7ef48a.png",
        "country": "CH",
        "rewardOptions": [
          {
            "id": "1haw82vD6WDxtOk4bwj8PQ==",
            "type": {
              "key": "pos",
              "label": "pos"
            },
            "metrics": [
              {
                "metricKey": "assets_under_management",
                "defaultValue": 1867810.069330491
              },
              {
                "metricKey": "available_capacity",
                "defaultValue": 0
              }
            ]
          },
          {
            "id": "5d34930fe03dd8000780b7bc",
            "type": {
              "key": "pos",
              "label": "pos"
            },
            "metrics": [
              {
                "metricKey": "assets_under_management",
                "defaultValue": 11917251.552802414
              },
              {
                "metricKey": "available_capacity",
                "defaultValue": 0
              }
            ]
          },
          {
            "id": "5da99e27f72d5f00081e53de",
            "type": {
              "key": "pos",
              "label": "pos"
            },
            "metrics": [
              {
                "metricKey": "assets_under_management",
                "defaultValue": 4911612.685263445
              },
              {
                "metricKey": "available_capacity",
                "defaultValue": 445975.9188409995
              }
            ]
          },
          {
            "id": "5eda48e7ec338500073ed615",
            "type": {
              "key": "pos",
              "label": "pos"
            },
            "metrics": [
              {
                "metricKey": "assets_under_management",
                "defaultValue": 0
              },
              {
                "metricKey": "available_capacity",
                "defaultValue": 0
              }
            ]
          },
          {
            "id": "5ff6d5221acf780007736bc3",
            "type": {
              "key": "pos",
              "label": "pos"
            },
            "metrics": [
              {
                "metricKey": "assets_under_management",
                "defaultValue": 5162895.9139638515
              },
              {
                "metricKey": "available_capacity",
                "defaultValue": 0
              }
            ]
          }
        ]
      },
      {
        "name": "Simple POS Pool",
        "logoUrl": "https://cms.stakingrewards.com/wp-content/uploads/2019/05/simplepospool.png",
        "country": null,
        "rewardOptions": null
      },
      {
        "name": "Stakinglab",
        "logoUrl": "https://cms.stakingrewards.com/wp-content/uploads/2019/05/stakinglab.png",
        "country": "de",
        "rewardOptions": null
      }
    ]
  }
}